MANIFEST.in
README.md
pyproject.toml
requirements-dev.txt
requirements-test.txt
requirements.txt
setup.cfg
setup.py
tox.ini
locker/__about__.json
locker/__about__.py
locker/__init__.py
locker/atomic_locking.py
locker/binary_adapter.py
locker/client.py
locker/error.py
locker/logger.py
locker/ls_logger.py
locker/ls_object.py
locker/ls_response.py
locker/object_classes.py
locker/util.py
locker/ls_resources/__init__.py
locker/ls_resources/environment.py
locker/ls_resources/error_object.py
locker/ls_resources/secret.py
locker/ls_resources/abstract/__init__.py
locker/ls_resources/abstract/api_resource.py
locker/ls_resources/abstract/createable_api_resource.py
locker/ls_resources/abstract/deletable_api_resource.py
locker/ls_resources/abstract/detailable_api_resource.py
locker/ls_resources/abstract/listable_api_resource.py
locker/ls_resources/abstract/singleton_api_resource.py
locker/ls_resources/abstract/updateable_api_resource.py
lockerpm.egg-info/PKG-INFO
lockerpm.egg-info/SOURCES.txt
lockerpm.egg-info/dependency_links.txt
lockerpm.egg-info/requires.txt
lockerpm.egg-info/top_level.txt
tests/__init__.py
tests/test_binary_adapter.py
tests/test_client.py
tests/test_logger.py
tests/test_util.py